offloading/__about__.py
offloading/__init__.py
offloading-2.0.0.dist-info/METADATA
offloading-2.0.0.dist-info/WHEEL
offloading-2.0.0.dist-info/licenses/LICENSE
offloading-2.0.0.dist-info/RECORD
