Metadata-Version: 2.1
Name: offloading
Version: 2.0.0
Summary: Offloading tasks in threads or processes
Project-URL: Documentation, https://github.com/jackcvr/offloading#readme
Project-URL: Issues, https://github.com/jackcvr/offloading/issues
Project-URL: Source, https://github.com/jackcvr/offloading
Author-email: Andrii Kuzmin <jack.cvr@gmail.com>
License-Expression: MIT
License-File: LICENSE
Classifier: Development Status :: 4 - Beta
Classifier: Programming Language :: Python
Classifier: Programming Language :: Python :: 3.7
Classifier: Programming Language :: Python :: 3.8
Classifier: Programming Language :: Python :: 3.9
Classifier: Programming Language :: Python :: 3.10
Classifier: Programming Language :: Python :: 3.11
Classifier: Programming Language :: Python :: Implementation :: CPython
Classifier: Programming Language :: Python :: Implementation :: PyPy
Requires-Python: >=3.7
